bots/__init__.py
bots/admin.py
bots/apachewebserver.py
bots/automaticmaintenance.py
bots/bots_context.py
bots/bots_importlib.py
bots/bots_ordereddict.py
bots/botsconfig.py
bots/botsglobal.py
bots/botsinit.py
bots/botslib.py
bots/botssqlite.py
bots/botsupdatedb.py
bots/cleanup.py
bots/communication.py
bots/dirmonitor.py
bots/engine.py
bots/engine2.py
bots/envelope.py
bots/forms.py
bots/grammar.py
bots/grammarcheck.py
bots/inmessage.py
bots/job2queue.py
bots/jobqueueserver.py
bots/message.py
bots/models.py
bots/node.py
bots/outmessage.py
bots/persistfilters.py
bots/pluglib.py
bots/plugoutindex.py
bots/preprocess.py
bots/py2html.py
bots/router.py
bots/transform.py
bots/urls.py
bots/validate_email.py
bots/viewlib.py
bots/views.py
bots/webserver.py
bots/xml2botsgrammar.py
bots/config/__init__.py
bots/config/bots.ini
bots/config/settings.py
bots/install/bots.ini
bots/install/botsdb
bots/install/settings.py
bots/locale/nl/LC_MESSAGES/django.mo
bots/locale/nl/LC_MESSAGES/django.po
bots/media/admin/css/base.css
bots/media/admin/css/changelists.css
bots/media/admin/css/dashboard.css
bots/media/admin/css/forms.css
bots/media/admin/css/ie.css
bots/media/admin/css/login.css
bots/media/admin/css/rtl.css
bots/media/admin/css/widgets.css
bots/media/admin/img/changelist-bg.gif
bots/media/admin/img/changelist-bg_rtl.gif
bots/media/admin/img/chooser-bg.gif
bots/media/admin/img/chooser_stacked-bg.gif
bots/media/admin/img/default-bg-reverse.gif
bots/media/admin/img/default-bg.gif
bots/media/admin/img/deleted-overlay.gif
bots/media/admin/img/icon-no.gif
bots/media/admin/img/icon-unknown.gif
bots/media/admin/img/icon-yes.gif
bots/media/admin/img/icon_addlink.gif
bots/media/admin/img/icon_alert.gif
bots/media/admin/img/icon_calendar.gif
bots/media/admin/img/icon_changelink.gif
bots/media/admin/img/icon_clock.gif
bots/media/admin/img/icon_deletelink.gif
bots/media/admin/img/icon_error.gif
bots-3.3.0.dist-info/DESCRIPTION.rst
bots-3.3.0.dist-info/METADATA
bots-3.3.0.dist-info/RECORD
bots-3.3.0.dist-info/WHEEL
bots-3.3.0.dist-info/metadata.json
bots-3.3.0.dist-info/top_level.txt
