Metadata-Version: 2.0
Name: bots
Version: 3.3.0
Summary: Bots open source edi translator
Home-page: https://github.com/bots-edi/bots
Author: hjebbers
Author-email: hjebbers@gmail.com
License: GNU General Public License (GPL)
Keywords: edi edifact x12 tradacoms xml fixedfile csv
Platform: OS Independent (Written in an interpreted language)
Classifier: Development Status :: 5 - Production/Stable
Classifier: Operating System :: OS Independent
Classifier: Programming Language :: Python
Classifier: Programming Language :: Python :: 2
Classifier: Programming Language :: Python :: 2.7
Classifier: Programming Language :: Python :: 3.4
Classifier: Programming Language :: Python :: 3.5
Classifier: License :: OSI Approved :: GNU General Public License (GPL)
Classifier: Topic :: Office/Business
Classifier: Topic :: Office/Business :: Financial
Classifier: Topic :: Other/Nonlisted Topic
Classifier: Topic :: Communications
Classifier: Environment :: Console
Classifier: Environment :: Web Environment
